[
    {
        "title": "",
        "authors": "",
        "journal": "Journal: Submitted",
        "doi": "",
        "landingLink": "/landing/haircell/",
        "pubmedId": "",
        "dataLink": "",
        "downloadLink": "",
        "image": "",
        "imageAlt": ""
    },
    {
        "title": "Cochlear organoids reveal transcriptional programs of postnatal hair cell differentiation from supporting cells",
        "authors": "Kalra, Edge, et al.",
        "journal": "Cell Rep. 2023 Nov 28;42(11):113421.",
        "doi": "10.1016/j.celrep.2023.113421",
        "landingLink": "",
        "pubmedId": "37952154",
        "dataLink": "https://umgear.org/p?l=Lgr5org",
        "downloadLink": "",
        "image": "/landing/hrp/paper_37952154_preview.png",
        "imageAlt": "Cochlear organoids reveal transcriptional programs of postnatal hair cell differentiation from supporting cells"
    },
    {
        "title": "Early Wnt Signaling Activation Promotes Inner Ear Differentiation via Cell Caudalization in Mouse Stem Cell-Derived Organoids",
        "authors": "Tang, Nelson, et al.",
        "journal": "Stem Cells. 2023 Jan 30;41(1):26-38",
        "doi": "10.1093/stmcls/sxac071",
        "landingLink": "",
        "pubmedId": "36153788",
        "dataLink": "",
        "downloadLink": "",
        "image": "/landing/hrp/paper_36153788_preview.png",
        "imageAlt": "Early Wnt Signaling Activation Promotes Inner Ear Differentiation via Cell Caudalization in Mouse Stem Cell-Derived Organoids"
    }
]
